SimplyServos.py
KitronikPicoSimplyServos-1.0.1.dist-info/LICENSE
KitronikPicoSimplyServos-1.0.1.dist-info/METADATA
KitronikPicoSimplyServos-1.0.1.dist-info/WHEEL
KitronikPicoSimplyServos-1.0.1.dist-info/top_level.txt
KitronikPicoSimplyServos-1.0.1.dist-info/RECORD
