Metadata-Version: 2.1
Name: KitronikPicoSimplyServos
Version: 1.0.1
Summary: Kitronik Simply Servo board for Raspberry Pi Pico allows for up to 8 servos to be controlled simultaneously
License-File: LICENSE
